{

	"damageMultiplier" : 15,
	"knockback" : 5,

	"magazineCapacity" : 30,
	"chamberAutoLoad" : true,
	"chamberEject" : true,

	"recoil" : 4,
	"recoilRecovery" : 2,
	"recoilResponse" : 2,
	"armRecoil" : 0.155,
	"armRecoilRecovery" : 2,
	
	"movingInaccuracy" : 5,
	"standingInaccuracy" : 0.5,
	"crouchInaccuracyMultiplier" : 0.5,

	"aimRatio" : 0.05,

	"firemode" : "auto",
	"rpm" : 950,

	"casing" : {
		"part" : "casingPosition",
		"type" : "5mm",
		"velocity" : [-2,10],
		"count" : 1
	},

	"projectileName" : "plasmabullet",
	"projectileConfig" : "/mpguns_core/projectileConfigs/bullet.config"
}